Metadata-Version: 2.1
Name: total-calculator
Version: 0.1
Summary: add two values and return their sum
Home-page: UNKNOWN
License: UNKNOWN
Platform: UNKNOWN
